README.md
package_info.json
setup.py
th2_common/__init__.py
th2_common.egg-info/PKG-INFO
th2_common.egg-info/SOURCES.txt
th2_common.egg-info/dependency_links.txt
th2_common.egg-info/requires.txt
th2_common.egg-info/top_level.txt
th2_common/schema/__init__.py
th2_common/schema/box/__init__.py
th2_common/schema/box/configuration/__init__.py
th2_common/schema/box/configuration/box_configuration.py
th2_common/schema/configuration/__init__.py
th2_common/schema/configuration/abstract_configuration.py
th2_common/schema/cradle/__init__.py
th2_common/schema/cradle/cradle_configuration.py
th2_common/schema/event/__init__.py
th2_common/schema/event/event_batch_queue.py
th2_common/schema/event/event_batch_router.py
th2_common/schema/event/event_batch_sender.py
th2_common/schema/event/event_batch_subscriber.py
th2_common/schema/exception/__init__.py
th2_common/schema/exception/common_factory_error.py
th2_common/schema/exception/configuration_error.py
th2_common/schema/exception/grpc_router_error.py
th2_common/schema/exception/init_grpc_router_error.py
th2_common/schema/exception/no_connection_to_send_error.py
th2_common/schema/exception/router_error.py
th2_common/schema/factory/__init__.py
th2_common/schema/factory/abstract_common_factory.py
th2_common/schema/factory/common_factory.py
th2_common/schema/filter/__init__.py
th2_common/schema/filter/strategy/__init__.py
th2_common/schema/filter/strategy/filter_strategy.py
th2_common/schema/filter/strategy/impl/__init__.py
th2_common/schema/filter/strategy/impl/default_filter_strategy.py
th2_common/schema/grpc/__init__.py
th2_common/schema/grpc/configuration/__init__.py
th2_common/schema/grpc/configuration/grpc_endpoint_configuration.py
th2_common/schema/grpc/configuration/grpc_raw_filter_strategy.py
th2_common/schema/grpc/configuration/grpc_raw_robin_strategy.py
th2_common/schema/grpc/configuration/grpc_router_configuration.py
th2_common/schema/grpc/configuration/grpc_router_filter_configuration.py
th2_common/schema/grpc/configuration/grpc_server_configuration.py
th2_common/schema/grpc/configuration/grpc_service_configuration.py
th2_common/schema/grpc/router/__init__.py
