Metadata-Version: 2.1
Name: th2-common
Version: 3.5.4
Summary: th2_common
Home-page: https://github.com/th2-net/th2-common-py
Author: TH2-devs
Author-email: th2-devs@exactprosystems.com
License: Apache License 2.0
Platform: UNKNOWN
Requires-Python: >=3.7
